mylib002/__init__.py
mylib002-0.1.dist-info/LICENSE.txt
mylib002-0.1.dist-info/METADATA
mylib002-0.1.dist-info/WHEEL
mylib002-0.1.dist-info/top_level.txt
mylib002-0.1.dist-info/RECORD
